robustmq/__init__.py
robustmq/client.py
robustmq-0.0.2.dist-info/METADATA
robustmq-0.0.2.dist-info/WHEEL
robustmq-0.0.2.dist-info/licenses/LICENSE
robustmq-0.0.2.dist-info/RECORD
