Metadata-Version: 2.3
Name: robustmq
Version: 0.0.2
Summary: A robust mqtt library with message caching
Project-URL: Homepage, https://github.com/DaqOpen/robustmq
Project-URL: Issues, https://github.com/DaqOpen/robustmq/issues
Author-email: Michael Oberhofer <info@pqopen.com>
License-File: LICENSE
Classifier: License :: OSI Approved :: MIT License
Classifier: Operating System :: OS Independent
Classifier: Programming Language :: Python :: 3
Requires-Python: >=3.8
Requires-Dist: paho-mqtt
